{
  "name": "St. Paul's (Blood)",
  "type": "Residential",
  "location": {
    "province": "Alberta",
    "city": "Cardston",
    "latLng": {
      "lat": 49.29872222,
      "-113.3441": 0.000
    }
  },
  "narrativeDate": "09-11-01",
  "startYear": 1893,
  "endYear": 1975,
  "data": {
    "nameVariants": [],
    "chronoHistory": [],
    "notesHistory": [],
    "management": [],
    "enrollment": [],
    "reserves": ["aklavik", "blackfoot", "blackfoot", "blood", "cardston", "carlton", "cree", "gleichen", "johnSmith", "longPlain", "mosquito", "peigan", "sarcee", "splitLake", "yorkFactory"],
    "religiousGroups": [{
      "group": "group",
      "ref": ["number"]
    }, {
      "group": "group",
      "ref": ["number"]
    }, {
      "group": "group",
      "ref": ["number"]
    }, {
      "group": "group",
      "ref": ["number"]
    }],
    "writtenAgreements": [],
    "additionalInformation": []
  }
}
